fianchetto_tradebot_quickstart/__init__.py
fianchetto_tradebot_quickstart/sample/__init__.py
fianchetto_tradebot_quickstart/sample/main.py
fianchetto_tradebot_quickstart/sample/runnable_service.py
fianchetto_tradebot_quickstart-0.0.6.dist-info/licenses/LICENSE
fianchetto_tradebot_quickstart-0.0.6.dist-info/METADATA
fianchetto_tradebot_quickstart-0.0.6.dist-info/WHEEL
fianchetto_tradebot_quickstart-0.0.6.dist-info/top_level.txt
fianchetto_tradebot_quickstart-0.0.6.dist-info/RECORD
